telingo/__init__.py
telingo/__main__.py
telingo/util.py
telingo/theory/__init__.py
telingo/theory/body.py
telingo/theory/formula.py
telingo/theory/head.py
telingo/theory/path.py
telingo/transformers/__init__.py
telingo/transformers/head.py
telingo/transformers/program.py
telingo/transformers/term.py
telingo/transformers/transformer.py
telingo-2.1.3.dist-info/LICENSE.md
telingo-2.1.3.dist-info/METADATA
telingo-2.1.3.dist-info/WHEEL
telingo-2.1.3.dist-info/entry_points.txt
telingo-2.1.3.dist-info/top_level.txt
telingo-2.1.3.dist-info/RECORD
