Metadata-Version: 2.1
Name: telingo
Version: 2.1.3
Summary: System to solve dynamic temporal logic programs.
Home-page: https://github.com/potassco/telingo
Author: Roland Kaminski & Francois Laferriere
Author-email: kaminski@cs.uni-potsdam.de
License: MIT
License-File: LICENSE.md
Requires-Dist: clingo >=5.6
